Metadata-Version: 2.1
Name: retico-speechbraintts
Version: 0.1.2
Summary: Local speechbrain speech synthesis for retico.
Home-page: https://github.com/retico-team/retico-speechbraintts
Download-URL: https://github.com/retico-team/retico-speechbraintts
Author: Thilo Michael
Author-email: uhlomuhlo@gmail.com
Keywords: retico,framework,incremental,dialogue,dialog
Classifier: Development Status :: 2 - Pre-Alpha
Classifier: Programming Language :: Python :: 3
Classifier: License :: OSI Approved :: Apache Software License
Requires-Python: >=3.6, <4
License-File: LICENSE
